require/__init__.py
require/me.py
require_me-0.0.1.dist-info/LICENSE
require_me-0.0.1.dist-info/METADATA
require_me-0.0.1.dist-info/WHEEL
require_me-0.0.1.dist-info/top_level.txt
require_me-0.0.1.dist-info/RECORD
